urestapi/AUTHORS
urestapi/__init__.py
urestapi/main.py
urestapi/uptycs_rest_api.py
urestapi-2.0.3.dist-info/LICENSE
urestapi-2.0.3.dist-info/METADATA
urestapi-2.0.3.dist-info/WHEEL
urestapi-2.0.3.dist-info/entry_points.txt
urestapi-2.0.3.dist-info/top_level.txt
urestapi-2.0.3.dist-info/RECORD
