Metadata-Version: 2.1
Name: urestapi
Version: 2.0.3
Summary: Uptycs Rest API call highlighting.
Home-page: UNKNOWN
Author: vkumar
Author-email: vibhor.aim@gmail.com
License: BSD
Platform: UNKNOWN
Classifier: Intended Audience :: Developers
Classifier: License :: OSI Approved :: BSD License
Classifier: Operating System :: Unix
Classifier: Programming Language :: Python
Classifier: Programming Language :: Python :: 2
Classifier: Programming Language :: Python :: 2.7
Classifier: Programming Language :: Python :: 3
Classifier: Programming Language :: Python :: 3.4
Classifier: Programming Language :: Python :: 3.5
Classifier: Programming Language :: Python :: 3.6
Classifier: Programming Language :: Python :: 3.7
Classifier: Programming Language :: SQL
Classifier: Topic :: Database
Classifier: Topic :: Database :: Front-Ends
Classifier: Topic :: Software Development
Classifier: Topic :: Software Development :: Libraries :: Python Modules
Requires-Dist: click (>=4.1)
Requires-Dist: Pygments (>=1.6)
Requires-Dist: prompt-toolkit (>=3.0.8)
Requires-Dist: cli-helpers[styles] (>=1.0.1)
Requires-Dist: PyJWT (>=2.4.0)
Requires-Dist: requests
Requires-Dist: urllib3 (>=1.21.1)
